funpypi/__init__.py
funpypi/script.py
funpypi/setuptool.py
funpypi/version.py
funpypi-0.2.1.dist-info/LICENSE
funpypi-0.2.1.dist-info/METADATA
funpypi-0.2.1.dist-info/WHEEL
funpypi-0.2.1.dist-info/entry_points.txt
funpypi-0.2.1.dist-info/top_level.txt
funpypi-0.2.1.dist-info/RECORD
