Metadata-Version: 2.1
Name: funpypi
Version: 0.2.1
Summary: funpypi
Home-page: https://github.com/farfarfun/funpypi
Author: bingtao
Author-email: 1007530194@qq.com
License-File: LICENSE
